docconverter/__init__.py
docconverter/doc_converter_factory.py
docconverter/core/__init__.py
docconverter/core/converter_base.py
docconverter/implements/__init__.py
docconverter/implements/pdf_to_txt_converter.py
docconverter/implements/pdf_to_xlsx_converter.py
tests/__init__.py
tests/pdf_to_txt_converter_test.py
tests/pdf_to_xlsx_converter_test.py
CoDocConverter-0.2.2.dist-info/LICENSE.txt
CoDocConverter-0.2.2.dist-info/METADATA
CoDocConverter-0.2.2.dist-info/WHEEL
CoDocConverter-0.2.2.dist-info/top_level.txt
CoDocConverter-0.2.2.dist-info/RECORD
