Metadata-Version: 2.1
Name: CoDocConverter
Version: 0.2.2
Summary: 文档转换器
Home-page: https://www.cityocean.com
Author: CityOcean
Author-email: it@cityocean.com
License: GPL
Keywords: document,convert
Platform: UNKNOWN
Classifier: Intended Audience :: Developers
Classifier: License :: OSI Approved :: BSD License
Classifier: Programming Language :: Python
Classifier: Programming Language :: Python :: 3.8
Classifier: Programming Language :: Python :: 3.9
Classifier: Operating System :: OS Independent
Classifier: Topic :: Software Development :: Libraries :: Python Modules
Requires-Python: >=3.6
License-File: LICENSE.txt
Requires-Dist: pdfminer
